wijisqs/__init__.py
wijisqs/__version__.py
wijisqs/broker.py
wijisqs/buffer.py
wijisqs/timer.py
wijisqs/utils.py
wijisqs-0.4.3.dist-info/METADATA
wijisqs-0.4.3.dist-info/WHEEL
wijisqs-0.4.3.dist-info/top_level.txt
wijisqs-0.4.3.dist-info/RECORD
